coovts/__init__.py
coovts/errors.py
coovts/plugin.py
coovts/request.py
coovts/utils.py
coovts/types/__init__.py
coovts/types/plugin_api.py
coovts/types/plugin_api.pyi
coovts/types/shared.py
coovts/types/api/__init__.py
coovts/types/api/art_mesh.py
coovts/types/api/auth.py
coovts/types/api/error.py
coovts/types/api/event.py
coovts/types/api/expression.py
coovts/types/api/hotkey.py
coovts/types/api/info.py
coovts/types/api/item.py
coovts/types/api/model.py
coovts/types/api/ndi.py
coovts/types/api/param.py
coovts/types/api/physics.py
coovts/types/api/post_process.py
coovts/types/api/scene.py
coovts/types/event/__init__.py
coovts/types/event/event.py
coovts-0.0.1a2.dist-info/METADATA
coovts-0.0.1a2.dist-info/WHEEL
coovts-0.0.1a2.dist-info/licenses/LICENSE
coovts-0.0.1a2.dist-info/RECORD
