Metadata-Version: 2.4
Name: coovts
Version: 0.0.1a2
Summary: Another library for making VTube Studio plugins with Python
Author-email: LgCookie <lgc2333@126.com>
License-File: LICENSE
Requires-Python: >=3.12
Requires-Dist: cookit[pydantic]>=0.11.6
Requires-Dist: pydantic>=2.11.4
Requires-Dist: websockets>=15.0.1
